{"data":{"symbol":"PM","companyName":"Philip Morris International Inc Common Stock","stockType":"Common Stock","exchange":"NYSE","isNasdaqListed":false,"isNasdaq100":false,"isHeld":false,"primaryData":{"lastSalePrice":"$85.27","netChange":"UNCH","percentageChange":"","deltaIndicator":"unch","lastTradeTimestamp":"DATA AS OF Dec 20, 2019 7:39 PM ET - AFTER HOURS","isRealTime":true},"secondaryData":{"lastSalePrice":"$85.27","netChange":"0.72","percentageChange":"0.84%","deltaIndicator":"down","lastTradeTimestamp":"CLOSED AT 4:00 PM ET ON Dec 20, 2019","isRealTime":false},"keyStats":{"Volume":{"label":"Volume","value":"2,489,697"},"PreviousClose":{"label":"Previous Close","value":"$85.99"},"OpenPrice":{"label":"Open","value":"$86.88"},"MarketCap":{"label":"Market Cap","value":"132,669,428,933"}},"marketStatus":"After Hours","assetClass":"STOCKS"},"message":null,"status":{"rCode":200,"bCodeMessage":null,"developerMessage":null}}