{"data":{"symbol":"VZ","companyName":"Verizon Communications Inc. Common Stock","stockType":"Common Stock","exchange":"Dual Listed","isNasdaqListed":false,"isNasdaq100":false,"isHeld":false,"primaryData":{"lastSalePrice":"$61.94","netChange":"0.13","percentageChange":"0.21%","deltaIndicator":"down","lastTradeTimestamp":"DATA AS OF Dec 20, 2019 7:39 PM ET - AFTER HOURS","isRealTime":true},"secondaryData":{"lastSalePrice":"$62.07","netChange":"1.27","percentageChange":"2.09%","deltaIndicator":"up","lastTradeTimestamp":"CLOSED AT 4:00 PM ET ON Dec 20, 2019","isRealTime":false},"keyStats":{"Volume":{"label":"Volume","value":"20,377,850"},"PreviousClose":{"label":"Previous Close","value":"$60.80"},"OpenPrice":{"label":"Open","value":"$61.37"},"MarketCap":{"label":"Market Cap","value":"256,708,125,853"}},"marketStatus":"After Hours","assetClass":"STOCKS"},"message":null,"status":{"rCode":200,"bCodeMessage":null,"developerMessage":null}}